milgeo/__init__.py
milgeo/builder.py
milgeo/color.py
milgeo/config.py
milgeo/enum.py
milgeo/extractor.py
milgeo/geometry.py
milgeo/kropyva/__init__.py
milgeo/kropyva/mapping.csv
milgeo/kropyva/url_mapping.py
milgeo/kropyva/tactics/__init__.py
milgeo/kropyva/tactics/extractor.py
milgeo/kropyva/tactics/high_level.py
milgeo/kropyva/tactics/low_level.py
milgeo/utils/__init__.py
milgeo/utils/coords.py
milgeo/utils/datetime_utils.py
milgeo/utils/iter_utils.py
milgeo/utils/kme_utils.py
milgeo/utils/kml_utils.py
milgeo/utils/kmz_utils.py
milgeo/utils/milsymbol.py
milgeo/utils/sidc_utlis.py
milgeo/utils/svg_utils.py
tests/__init__.py
tests/test_builder.py
tests/test_color.py
tests/test_geometry.py
tests/test_iter_utils.py
tests/test_tactics.py
milgeo-0.5.8.dist-info/METADATA
milgeo-0.5.8.dist-info/WHEEL
milgeo-0.5.8.dist-info/top_level.txt
milgeo-0.5.8.dist-info/RECORD
