Metadata-Version: 2.2
Name: milgeo
Version: 0.5.8
Summary: Common geometries for mil applications
Home-page: https://github.com/adamwoodintel/milgeo
Author: Adam Wood
Author-email: adamwoodintel@gmail.com
Requires-Python: >=3.11
Requires-Dist: setuptools==70.2.0
Requires-Dist: pytest==8.2.2
Requires-Dist: webcolors==24.6.0
Requires-Dist: text_to_sidc>=0.0.13
Requires-Dist: lxml==4.9.2
Requires-Dist: military-symbol==1.0.0
Requires-Dist: CairoSVG==2.7.1
Requires-Dist: js2py==0.74
Requires-Dist: pycryptodome==3.20.0
Requires-Dist: pykml==0.2.0
Requires-Dist: svgpathtools==1.6.1
Requires-Dist: build
Requires-Dist: html2text>=2024.2.26
Requires-Dist: pyproj==3.6.1
Dynamic: author
Dynamic: author-email
Dynamic: description
Dynamic: description-content-type
Dynamic: home-page
Dynamic: requires-dist
Dynamic: requires-python
Dynamic: summary
